Metadata-Version: 1.1
Name: SteamQuery
Version: 1.0.2
Summary: A library for querying steam game servers
Home-page: https://github.com/Jason2605/SteamQuery
Author: Jason Hall
Author-email: jasonhall96686@gmail.com
License: General Public License v3.0
Platform: UNKNOWN
Classifier: Development Status :: 4 - Beta
Classifier: Intended Audience :: Developers
Classifier: Programming Language :: Python :: 3
